{
  "city": "Tbilisi",
  "country": "Georgia",
  "airportPostcode": "0108",
  "airportDistanceKm": 18,
  "things": [
    {
      "rank": 1,
      "name": "Old Town (Abanotubani Sulphur Baths)",
      "description": "Historic Metekhi district with natural hot sulphur public baths used for 1,500 years"
    },
    {
      "rank": 2,
      "name": "Narikala Fortress",
      "description": "4th-century fortress above the city with a cable car and panoramic views of the Mtkvari River"
    },
    {
      "rank": 3,
      "name": "Mtatsminda Park & Funicular",
      "description": "Mountain park reached by funicular with an amusement park and spectacular city views"
    },
    {
      "rank": 4,
      "name": "Georgian National Museum",
      "description": "Gold treasures, medieval art and Georgian history from Paleolithic to Soviet times"
    },
    {
      "rank": 5,
      "name": "Sioni Cathedral",
      "description": "6th-century Georgian Orthodox cathedral housing the 4th-century Cross of St Nino"
    },
    {
      "rank": 6,
      "name": "Rustaveli Avenue",
      "description": "Tbilisi's main boulevard with the Opera House, Parliament and Art Museum"
    },
    {
      "rank": 7,
      "name": "Kazbegi National Park Day Trip",
      "description": "Gergeti Trinity Church on a cliff with Mount Kazbek (5047m) as a backdrop"
    },
    {
      "rank": 8,
      "name": "Georgian Wine & Qvevri Wine Tourism",
      "description": "Georgia's 8,000-year wine tradition using clay qvevri amphorae - world's oldest wine culture"
    },
    {
      "rank": 9,
      "name": "Peace Bridge",
      "description": "Striking 2010 pedestrian bridge over the Kura River designed by Italian architect Michele De Lucchi"
    },
    {
      "rank": 10,
      "name": "Fabrika",
      "description": "Soviet sewing factory converted into Tbilisi's hippest hostel, co-working and nightlife complex"
    }
  ]
}
