{
  "city": "Valencia",
  "country": "Spain",
  "airportPostcode": "46940",
  "airportDistanceKm": 9,
  "things": [
    {
      "rank": 1,
      "name": "City of Arts and Sciences",
      "postcode": "46013",
      "distanceKmFromAirport": 12,
      "description": "Santiago Calatrava's breathtaking futuristic complex with science museum, IMAX and oceanarium",
      "distance": 3.5,
      "URL": "https://www.cac.es/en/"
    },
    {
      "rank": 2,
      "name": "Valencia Cathedral & Holy Grail",
      "postcode": "46003",
      "distanceKmFromAirport": 10,
      "description": "Gothic cathedral that allegedly houses the Holy Grail — climb the Miguelete bell tower for city views",
      "distance": 0.5,
      "URL": "https://www.catedraldevalencia.es/en/"
    },
    {
      "rank": 3,
      "name": "Central Market (Mercado Central)",
      "postcode": "46001",
      "distanceKmFromAirport": 10,
      "description": "One of Europe's largest fresh food markets (1928) in a stunning Art Nouveau iron-and-tile building",
      "distance": 0.5,
      "URL": "https://www.mercadocentralvalencia.es/en/"
    },
    {
      "rank": 4,
      "name": "Turia Gardens",
      "postcode": "46010",
      "distanceKmFromAirport": 10,
      "description": "9-km linear park created in the dry bed of the River Turia — bike paths, sports and gardens",
      "distance": 1.0,
      "URL": "https://www.visitvalencia.com/en/"
    },
    {
      "rank": 5,
      "name": "La Malvarrosa Beach",
      "postcode": "46011",
      "distanceKmFromAirport": 14,
      "description": "Valencia's main urban beach — wide sandy promenade with excellent paella restaurants nearby",
      "distance": 5.0,
      "URL": "https://www.visitvalencia.com/en/"
    },
    {
      "rank": 6,
      "name": "Barrio del Carmen",
      "postcode": "46003",
      "distanceKmFromAirport": 9,
      "description": "Valencia's bohemian old town quarter with medieval walls, street art and the best tapas bars",
      "distance": 0.3,
      "URL": "https://www.visitvalencia.com/en/"
    },
    {
      "rank": 7,
      "name": "Museum of Fine Arts Valencia",
      "postcode": "46003",
      "distanceKmFromAirport": 10,
      "description": "One of Spain's most important collections with Ribalta, Sorolla and European Old Masters",
      "distance": 1.5,
      "URL": "https://www.museobellasartesvalencia.gva.es/en/"
    },
    {
      "rank": 8,
      "name": "L'Albufera Natural Park",
      "postcode": "46012",
      "distanceKmFromAirport": 19,
      "description": "Stunning freshwater lagoon 10 km south — the birthplace of paella, with boat trips and rice fields",
      "distance": 10.0,
      "URL": "https://www.visitvalencia.com/en/what-to-visit-valencia/natural-spaces/albufera"
    },
    {
      "rank": 9,
      "name": "Silk Exchange (La Lonja)",
      "postcode": "46001",
      "distanceKmFromAirport": 10,
      "description": "UNESCO World Heritage 15th-century Gothic silk trading hall with a stunning spiral-column hall",
      "distance": 0.5,
      "URL": "https://www.visitvalencia.com/en/"
    },
    {
      "rank": 10,
      "name": "IVAM Contemporary Art Museum",
      "postcode": "46003",
      "distanceKmFromAirport": 10,
      "description": "Spain's first dedicated contemporary art museum with a strong collection of avant-garde works",
      "distance": 1.0,
      "URL": "https://www.ivam.es/en/"
    }
  ]
}